AUTHORS
CHANGELOG.txt
DESCRIPTION
LICENSE
MANIFEST.in
README.md
manage.py
requirements.txt
setup.cfg
tox.ini
django_mailprotector.egg-info/PKG-INFO
django_mailprotector.egg-info/SOURCES.txt
django_mailprotector.egg-info/dependency_links.txt
django_mailprotector.egg-info/requires.txt
django_mailprotector.egg-info/top_level.txt
mailprotector/__init__.py
mailprotector/conf.py
mailprotector/minifier.py
mailprotector/models.py
mailprotector/protectors/__init__.py
mailprotector/protectors/ajax_captcha.py
mailprotector/protectors/ajax_recaptcha.py
mailprotector/protectors/ajax_uuid.py
mailprotector/protectors/munger.py
mailprotector/protectors/munger_link_only.py
mailprotector/templatetags/__init__.py
mailprotector/templatetags/mailprotector_tags.py
mailprotector/tests/.coveragerc
mailprotector/tests/__init__.py
mailprotector/tests/base.py
mailprotector/tests/factories.py
mailprotector/tests/settings.py
mailprotector/tests/settings_munger_link_only.py
mailprotector/tests/settings_no_headless.py
mailprotector/tests/test_munger.py
mailprotector/tests/test_munger_link_only.py
mailprotector/tests/urls.py
mailprotector/tests/test_app/__init__.py
mailprotector/tests/test_app/models.py
mailprotector/tests/test_app/templates/400.html
mailprotector/tests/test_app/templates/500.html
mailprotector/tests/test_app/templates/test_app/test.html
mailprotector/tests/utils/__init__.py
mailprotector/tests/utils/django_utils.py
mailprotector/tests/utils/selenium_utils.py
django_mailprotector-0.3.1.dist-info/AUTHORS
django_mailprotector-0.3.1.dist-info/LICENSE
django_mailprotector-0.3.1.dist-info/METADATA
django_mailprotector-0.3.1.dist-info/WHEEL
django_mailprotector-0.3.1.dist-info/top_level.txt
django_mailprotector-0.3.1.dist-info/RECORD
