Metadata-Version: 2.1
Name: django-mailprotector
Version: 0.3.1
Summary: A reusable Django app that protects email addresses and phone numbers, in various ways.
Home-page: https://github.com/bnzk/django-mailprotector
Author: Ben Stähli
Author-email: bnzk@bnzk.ch
License: MIT
Keywords: django,email,obfuscate
Platform: OS Independent
License-File: LICENSE
License-File: AUTHORS
Requires-Dist: django
Requires-Dist: six
Requires-Dist: django-appconf
Requires-Dist: beautifulsoup4
Provides-Extra: dev
Requires-Dist: tox ; extra == 'dev'
